{
    "leaderboard": [
        {
            "name": "CYOPEAR",
            "score": 5210
        },
        {
            "name": "CYOPEAR",
            "score": 5130
        },
        {
            "name": "CYOPEAR",
            "score": 4740
        },
        {
            "name": "CYOPEAR",
            "score": 1060
        },
        {
            "name": "CYOPEAR",
            "score": 910
        },
        {
            "name": "CYOPEAR",
            "score": 400
        },
        {
            "name": "CYOPEAR",
            "score": 400
        }
    ]
}